setup.py
komodo_google_auth/__init__.py
komodo_google_auth.egg-info/PKG-INFO
komodo_google_auth.egg-info/SOURCES.txt
komodo_google_auth.egg-info/dependency_links.txt
komodo_google_auth.egg-info/requires.txt
komodo_google_auth.egg-info/top_level.txt