Metadata-Version: 1.0
Name: komodo-google-auth
Version: 1.0.0
Summary: Plugin for Komodo dashboard that enables authentication behind a google login
Home-page: https://github.com/mic159/komodo-google-auth
Author: Michael Cooper
Author-email: mic159@gmail.com
License: MIT
Keywords: dashboard
Platform: UNKNOWN
